{
    "corsi": [
        "Python M",
        "Py",
        "Python",
        "HTML",
        "css"
    ],
    "partecipanti": [
        {
            "nome": "Manuela",
            "cognome": "Musmeci",
            "corso": "Python",
            "premi": [
                {
                    "quantita": 2,
                    "data": "07/01/2026 16:21:15"
                },
                {
                    "quantita": 1,
                    "data": "07/01/2026 16:41:17"
                }
            ]
        },
        {
            "nome": "Claudia Paperina",
            "cognome": "Di Peperopoli",
            "corso": "HTML",
            "premi": []
        },
        {
            "nome": "Claudia",
            "cognome": "Paperina",
            "corso": "Python",
            "premi": [
                {
                    "quantita": 4,
                    "data": "07/01/2026 16:40:36"
                }
            ]
        },
        {
            "nome": "Nicolò",
            "cognome": "Macchiavelli",
            "corso": "css",
            "premi": [
                {
                    "quantita": 7,
                    "data": "07/01/2026 16:49:34"
                }
            ]
        }
    ]
}